[
    {
        "user_id": "811104-11-9852",
        "transaction_id": "8ea6c705-6c2c-49fd-aca2-6e2643f56155",
        "client_id": 3130,
        "transaction_date": "2022-12-30T22:33:44.700112",
        "transaction_amount": 896,
        "transaction_details": "Home Appliances",
        "transacted_to": "787513-77-9847",
        "is_anomaly": "No",
        "anomaly_type": "Fraud",
        "user_score": 72,
        "coors": {
            "latitude": "3.202089",
            "longitude": "101.595644"
        }
    },
    {
        "user_id": "811104-11-9852",
        "transaction_id": "3550e0b7-6c17-4d95-b612-89d472871dc6",
        "client_id": 9728,
        "transaction_date": "2023-03-27T22:33:44.700112",
        "transaction_amount": 210,
        "transaction_details": "Electronics",
        "transacted_to": "858835-94-6784",
        "is_anomaly": "Yes",
        "anomaly_type": "Fraud",
        "user_score": 57,
        "coors": {
            "latitude": "3.194465",
            "longitude": "101.608993"
        }
    },
    {
        "user_id": "811104-11-9852",
        "transaction_id": "a55fdc91-c84b-4ebb-9558-3772653c5ac5",
        "client_id": 4091,
        "transaction_date": "2022-06-12T22:33:44.700112",
        "transaction_amount": 85,
        "transaction_details": "Books",
        "transacted_to": "296649-66-6823",
        "is_anomaly": "Yes",
        "anomaly_type": "",
        "user_score": 46,
        "coors": {
            "latitude": "3.232864",
            "longitude": "101.638443"
        }
    },
    {
        "user_id": "811104-11-9852",
        "transaction_id": "9453d3a2-9a18-4c91-b8d8-ae5ea52a3d0a",
        "client_id": 7335,
        "transaction_date": "2023-04-11T22:33:44.700112",
        "transaction_amount": 835,
        "transaction_details": "Home Appliances",
        "transacted_to": "833692-50-2913",
        "is_anomaly": "No",
        "anomaly_type": "",
        "user_score": 19,
        "coors": {
            "latitude": "3.118704",
            "longitude": "101.695349"
        }
    },
    {
        "user_id": "811104-11-9852",
        "transaction_id": "46d93289-7555-4ead-9eaa-df393d7e3fe2",
        "client_id": 3517,
        "transaction_date": "2022-09-20T22:33:44.700112",
        "transaction_amount": 47,
        "transaction_details": "Electronics",
        "transacted_to": "691883-85-5186",
        "is_anomaly": "No",
        "anomaly_type": "",
        "user_score": 77,
        "coors": {
            "latitude": "3.211597",
            "longitude": "101.616075"
        }
    },
    {
        "user_id": "811104-11-9852",
        "transaction_id": "4fec943e-b4a3-4688-af63-2736e1d24233",
        "client_id": 3555,
        "transaction_date": "2022-07-09T22:33:44.700112",
        "transaction_amount": 387,
        "transaction_details": "Clothing",
        "transacted_to": "936918-57-9144",
        "is_anomaly": "No",
        "anomaly_type": "Fraud",
        "user_score": 0,
        "coors": {
            "latitude": "3.125768",
            "longitude": "101.701133"
        }
    },
    {
        "user_id": "811104-11-9852",
        "transaction_id": "c298e039-4c00-494b-b382-63d0f0ae59d7",
        "client_id": 4415,
        "transaction_date": "2022-10-08T22:33:44.700112",
        "transaction_amount": 393,
        "transaction_details": "Clothing",
        "transacted_to": "486406-50-7217",
        "is_anomaly": "Yes",
        "anomaly_type": "Suspicious",
        "user_score": 83,
        "coors": {
            "latitude": "3.221288",
            "longitude": "101.736119"
        }
    },
    {
        "user_id": "811104-11-9852",
        "transaction_id": "f45ec46b-16c0-4344-ac0f-c1717b88f8b7",
        "client_id": 6676,
        "transaction_date": "2023-05-15T22:33:44.700112",
        "transaction_amount": 563,
        "transaction_details": "Electronics",
        "transacted_to": "108005-10-9900",
        "is_anomaly": "Yes",
        "anomaly_type": "Fraud",
        "user_score": 1,
        "coors": {
            "latitude": "3.068165",
            "longitude": "101.608258"
        }
    },
    {
        "user_id": "811104-11-9852",
        "transaction_id": "96d95183-b0cb-49a9-9032-d81070713ada",
        "client_id": 8974,
        "transaction_date": "2022-12-26T22:33:44.700112",
        "transaction_amount": 305,
        "transaction_details": "Clothing",
        "transacted_to": "118297-11-2286",
        "is_anomaly": "No",
        "anomaly_type": "Fraud",
        "user_score": 34,
        "coors": {
            "latitude": "3.177415",
            "longitude": "101.631234"
        }
    },
    {
        "user_id": "811104-11-9852",
        "transaction_id": "e169da65-9be4-4b79-b353-7bacd4d818d7",
        "client_id": 4487,
        "transaction_date": "2022-09-06T22:33:44.700112",
        "transaction_amount": 491,
        "transaction_details": "Books",
        "transacted_to": "935520-89-6943",
        "is_anomaly": "No",
        "anomaly_type": "Fraud",
        "user_score": 58,
        "coors": {
            "latitude": "3.065464",
            "longitude": "101.637808"
        }
    },
    {
        "user_id": "811104-11-9852",
        "transaction_id": "91b9858e-56f4-421a-bc0d-16437fb6fa4c",
        "client_id": 8344,
        "transaction_date": "2022-06-05T22:33:44.700112",
        "transaction_amount": 709,
        "transaction_details": "Home Appliances",
        "transacted_to": "274615-21-5688",
        "is_anomaly": "No",
        "anomaly_type": "Suspicious",
        "user_score": 21,
        "coors": {
            "latitude": "3.229838",
            "longitude": "101.619781"
        }
    },
    {
        "user_id": "811104-11-9852",
        "transaction_id": "c5b1b4e9-f4f3-473b-a35a-4f926746f94b",
        "client_id": 1362,
        "transaction_date": "2023-01-01T22:33:44.700112",
        "transaction_amount": 148,
        "transaction_details": "Clothing",
        "transacted_to": "140897-20-2666",
        "is_anomaly": "Yes",
        "anomaly_type": "Suspicious",
        "user_score": 50,
        "coors": {
            "latitude": "3.079959",
            "longitude": "101.729513"
        }
    },
    {
        "user_id": "811104-11-9852",
        "transaction_id": "3ade7ad4-587c-412c-a0ae-bde7966bb08d",
        "client_id": 8883,
        "transaction_date": "2023-04-05T22:33:44.700112",
        "transaction_amount": 557,
        "transaction_details": "Home Appliances",
        "transacted_to": "590688-49-6827",
        "is_anomaly": "No",
        "anomaly_type": "",
        "user_score": 53,
        "coors": {
            "latitude": "3.050701",
            "longitude": "101.705728"
        }
    },
    {
        "user_id": "811104-11-9852",
        "transaction_id": "260b69fd-1a16-460e-a665-f79286966d6e",
        "client_id": 8261,
        "transaction_date": "2022-08-22T22:33:44.700112",
        "transaction_amount": 454,
        "transaction_details": "Clothing",
        "transacted_to": "875043-71-2136",
        "is_anomaly": "No",
        "anomaly_type": "Suspicious",
        "user_score": 53,
        "coors": {
            "latitude": "3.162796",
            "longitude": "101.690152"
        }
    },
    {
        "user_id": "811104-11-9852",
        "transaction_id": "8fc5ded4-2382-4d55-bde7-78b70c315f5f",
        "client_id": 7904,
        "transaction_date": "2023-05-07T22:33:44.700112",
        "transaction_amount": 147,
        "transaction_details": "Books",
        "transacted_to": "978671-77-5793",
        "is_anomaly": "Yes",
        "anomaly_type": "Suspicious",
        "user_score": 15,
        "coors": {
            "latitude": "3.120044",
            "longitude": "101.702159"
        }
    },
    {
        "user_id": "811104-11-9852",
        "transaction_id": "c41346bb-83cb-48aa-9405-6f1688cbcb91",
        "client_id": 2740,
        "transaction_date": "2022-06-16T22:33:44.700112",
        "transaction_amount": 651,
        "transaction_details": "Home Appliances",
        "transacted_to": "885159-15-6797",
        "is_anomaly": "Yes",
        "anomaly_type": "",
        "user_score": 59,
        "coors": {
            "latitude": "3.094194",
            "longitude": "101.604040"
        }
    },
    {
        "user_id": "811104-11-9852",
        "transaction_id": "123199cd-6b38-4568-93f0-524f361700c9",
        "client_id": 4223,
        "transaction_date": "2022-06-22T22:33:44.700112",
        "transaction_amount": 377,
        "transaction_details": "Clothing",
        "transacted_to": "290922-60-4154",
        "is_anomaly": "Yes",
        "anomaly_type": "Fraud",
        "user_score": 80,
        "coors": {
            "latitude": "3.167032",
            "longitude": "101.640154"
        }
    },
    {
        "user_id": "811104-11-9852",
        "transaction_id": "667a6d60-07e1-48ad-b779-056827a89609",
        "client_id": 9731,
        "transaction_date": "2022-09-11T22:33:44.700112",
        "transaction_amount": 374,
        "transaction_details": "Books",
        "transacted_to": "603367-72-9888",
        "is_anomaly": "Yes",
        "anomaly_type": "",
        "user_score": 93,
        "coors": {
            "latitude": "3.178021",
            "longitude": "101.653418"
        }
    },
    {
        "user_id": "811104-11-9852",
        "transaction_id": "d6bec966-bf49-4480-9bae-60e80e68ccb8",
        "client_id": 4424,
        "transaction_date": "2023-03-17T22:33:44.700112",
        "transaction_amount": 284,
        "transaction_details": "Clothing",
        "transacted_to": "467859-33-9757",
        "is_anomaly": "Yes",
        "anomaly_type": "",
        "user_score": 66,
        "coors": {
            "latitude": "3.209367",
            "longitude": "101.622117"
        }
    },
    {
        "user_id": "811104-11-9852",
        "transaction_id": "59355cd7-fa2f-40ff-be7f-081507340357",
        "client_id": 7559,
        "transaction_date": "2023-01-11T22:33:44.700112",
        "transaction_amount": 320,
        "transaction_details": "Electronics",
        "transacted_to": "422810-66-8669",
        "is_anomaly": "Yes",
        "anomaly_type": "Fraud",
        "user_score": 39,
        "coors": {
            "latitude": "3.133479",
            "longitude": "101.663907"
        }
    },
    {
        "user_id": "811104-11-9852",
        "transaction_id": "9dbe3d91-0927-4726-8f9c-4fce7266f8f7",
        "client_id": 8506,
        "transaction_date": "2023-03-04T22:33:44.700112",
        "transaction_amount": 226,
        "transaction_details": "Electronics",
        "transacted_to": "666194-36-3021",
        "is_anomaly": "No",
        "anomaly_type": "Suspicious",
        "user_score": 24,
        "coors": {
            "latitude": "3.174838",
            "longitude": "101.607875"
        }
    },
    {
        "user_id": "811104-11-9852",
        "transaction_id": "1da87027-0dc7-4c8d-9afa-9ff1d7249297",
        "client_id": 6797,
        "transaction_date": "2023-03-11T22:33:44.700112",
        "transaction_amount": 276,
        "transaction_details": "Books",
        "transacted_to": "191965-38-2891",
        "is_anomaly": "Yes",
        "anomaly_type": "",
        "user_score": 71,
        "coors": {
            "latitude": "3.099281",
            "longitude": "101.614804"
        }
    },
    {
        "user_id": "811104-11-9852",
        "transaction_id": "63bd350f-a5a1-4b1e-a378-da803a067732",
        "client_id": 3469,
        "transaction_date": "2022-10-24T22:33:44.700112",
        "transaction_amount": 103,
        "transaction_details": "Clothing",
        "transacted_to": "504187-39-5406",
        "is_anomaly": "No",
        "anomaly_type": "",
        "user_score": 12,
        "coors": {
            "latitude": "3.188209",
            "longitude": "101.672045"
        }
    },
    {
        "user_id": "811104-11-9852",
        "transaction_id": "a9a5ff67-6a5d-4c88-bbd3-1506d2d4fcbc",
        "client_id": 5408,
        "transaction_date": "2022-12-07T22:33:44.700112",
        "transaction_amount": 955,
        "transaction_details": "Electronics",
        "transacted_to": "335478-48-8292",
        "is_anomaly": "Yes",
        "anomaly_type": "Suspicious",
        "user_score": 42,
        "coors": {
            "latitude": "3.172583",
            "longitude": "101.669301"
        }
    },
    {
        "user_id": "811104-11-9852",
        "transaction_id": "36e84744-006a-4871-a14f-9c224f59a6c3",
        "client_id": 7907,
        "transaction_date": "2023-05-23T22:33:44.700112",
        "transaction_amount": 509,
        "transaction_details": "Clothing",
        "transacted_to": "561673-54-7505",
        "is_anomaly": "Yes",
        "anomaly_type": "Fraud",
        "user_score": 89,
        "coors": {
            "latitude": "3.208134",
            "longitude": "101.717211"
        }
    },
    {
        "user_id": "811104-11-9852",
        "transaction_id": "a9ad5b98-ba81-4c4c-af4c-424f17446ce3",
        "client_id": 1813,
        "transaction_date": "2023-02-19T22:33:44.700112",
        "transaction_amount": 187,
        "transaction_details": "Clothing",
        "transacted_to": "136962-94-8197",
        "is_anomaly": "No",
        "anomaly_type": "",
        "user_score": 68,
        "coors": {
            "latitude": "3.057373",
            "longitude": "101.653679"
        }
    },
    {
        "user_id": "811104-11-9852",
        "transaction_id": "7cbdc03f-da65-456d-9fe9-0f48a6b6ecd2",
        "client_id": 4928,
        "transaction_date": "2023-03-20T22:33:44.700112",
        "transaction_amount": 847,
        "transaction_details": "Electronics",
        "transacted_to": "927771-67-1719",
        "is_anomaly": "No",
        "anomaly_type": "Fraud",
        "user_score": 71,
        "coors": {
            "latitude": "3.214968",
            "longitude": "101.658618"
        }
    },
    {
        "user_id": "811104-11-9852",
        "transaction_id": "2e11390c-fea8-43e2-ae61-6f8bf2608ef9",
        "client_id": 8948,
        "transaction_date": "2023-05-16T22:33:44.700112",
        "transaction_amount": 586,
        "transaction_details": "Home Appliances",
        "transacted_to": "969741-28-6886",
        "is_anomaly": "Yes",
        "anomaly_type": "",
        "user_score": 47,
        "coors": {
            "latitude": "3.099249",
            "longitude": "101.698330"
        }
    },
    {
        "user_id": "811104-11-9852",
        "transaction_id": "f869964d-c574-44c1-9d90-f7dfc5375487",
        "client_id": 4662,
        "transaction_date": "2022-11-09T22:33:44.700112",
        "transaction_amount": 565,
        "transaction_details": "Home Appliances",
        "transacted_to": "913174-66-7472",
        "is_anomaly": "Yes",
        "anomaly_type": "Fraud",
        "user_score": 82,
        "coors": {
            "latitude": "3.120137",
            "longitude": "101.719707"
        }
    },
    {
        "user_id": "811104-11-9852",
        "transaction_id": "0189ca59-b032-46d1-a12a-aab72b3adecb",
        "client_id": 5047,
        "transaction_date": "2023-03-07T22:33:44.700112",
        "transaction_amount": 419,
        "transaction_details": "Home Appliances",
        "transacted_to": "120113-41-7825",
        "is_anomaly": "No",
        "anomaly_type": "Suspicious",
        "user_score": 68,
        "coors": {
            "latitude": "3.067247",
            "longitude": "101.590315"
        }
    },
    {
        "user_id": "811104-11-9852",
        "transaction_id": "f566e801-7a69-4d91-a0e7-910c63b0e316",
        "client_id": 1971,
        "transaction_date": "2022-08-03T22:33:44.700112",
        "transaction_amount": 555,
        "transaction_details": "Home Appliances",
        "transacted_to": "697598-84-8719",
        "is_anomaly": "No",
        "anomaly_type": "",
        "user_score": 53,
        "coors": {
            "latitude": "3.151297",
            "longitude": "101.687437"
        }
    },
    {
        "user_id": "811104-11-9852",
        "transaction_id": "544ac972-67b8-4df4-b5e2-5421e5cd74c1",
        "client_id": 9225,
        "transaction_date": "2023-05-16T22:33:44.700112",
        "transaction_amount": 534,
        "transaction_details": "Clothing",
        "transacted_to": "338460-81-3361",
        "is_anomaly": "Yes",
        "anomaly_type": "Suspicious",
        "user_score": 91,
        "coors": {
            "latitude": "3.064444",
            "longitude": "101.726369"
        }
    },
    {
        "user_id": "811104-11-9852",
        "transaction_id": "7ac5ce4a-e88e-4191-9154-f687dac8b4fa",
        "client_id": 7421,
        "transaction_date": "2023-01-15T22:33:44.700112",
        "transaction_amount": 782,
        "transaction_details": "Clothing",
        "transacted_to": "369503-56-5115",
        "is_anomaly": "No",
        "anomaly_type": "",
        "user_score": 48,
        "coors": {
            "latitude": "3.142536",
            "longitude": "101.619576"
        }
    },
    {
        "user_id": "811104-11-9852",
        "transaction_id": "6d9c0199-f435-4a16-be6b-ce89cefdd16b",
        "client_id": 9059,
        "transaction_date": "2023-05-18T22:33:44.700112",
        "transaction_amount": 606,
        "transaction_details": "Home Appliances",
        "transacted_to": "316996-68-8578",
        "is_anomaly": "No",
        "anomaly_type": "",
        "user_score": 77,
        "coors": {
            "latitude": "3.212199",
            "longitude": "101.707385"
        }
    },
    {
        "user_id": "811104-11-9852",
        "transaction_id": "460a76e4-154e-402b-b7d3-df542d39f187",
        "client_id": 8493,
        "transaction_date": "2022-10-22T22:33:44.700112",
        "transaction_amount": 315,
        "transaction_details": "Electronics",
        "transacted_to": "620310-41-5433",
        "is_anomaly": "Yes",
        "anomaly_type": "Fraud",
        "user_score": 75,
        "coors": {
            "latitude": "3.133580",
            "longitude": "101.596922"
        }
    },
    {
        "user_id": "811104-11-9852",
        "transaction_id": "145b8c7e-cd5c-4b67-a40c-d1cc4bcab44f",
        "client_id": 3380,
        "transaction_date": "2023-03-25T22:33:44.700112",
        "transaction_amount": 506,
        "transaction_details": "Electronics",
        "transacted_to": "978936-10-6599",
        "is_anomaly": "Yes",
        "anomaly_type": "Fraud",
        "user_score": 66,
        "coors": {
            "latitude": "3.164676",
            "longitude": "101.645274"
        }
    },
    {
        "user_id": "811104-11-9852",
        "transaction_id": "8f4a08f4-e3c9-4ca6-8492-7714cc3ea271",
        "client_id": 5258,
        "transaction_date": "2023-03-14T22:33:44.700112",
        "transaction_amount": 643,
        "transaction_details": "Home Appliances",
        "transacted_to": "256998-23-4673",
        "is_anomaly": "No",
        "anomaly_type": "Suspicious",
        "user_score": 33,
        "coors": {
            "latitude": "3.156828",
            "longitude": "101.627551"
        }
    },
    {
        "user_id": "811104-11-9852",
        "transaction_id": "0b4d2abe-d092-4a86-8e1b-b68f0699815f",
        "client_id": 3976,
        "transaction_date": "2023-05-02T22:33:44.700112",
        "transaction_amount": 981,
        "transaction_details": "Electronics",
        "transacted_to": "516921-62-2638",
        "is_anomaly": "Yes",
        "anomaly_type": "",
        "user_score": 18,
        "coors": {
            "latitude": "3.199861",
            "longitude": "101.613109"
        }
    },
    {
        "user_id": "811104-11-9852",
        "transaction_id": "82f97720-f747-4779-a8de-bd1b08d5ea8a",
        "client_id": 4821,
        "transaction_date": "2022-11-06T22:33:44.700112",
        "transaction_amount": 384,
        "transaction_details": "Books",
        "transacted_to": "466038-92-7407",
        "is_anomaly": "No",
        "anomaly_type": "Fraud",
        "user_score": 56,
        "coors": {
            "latitude": "3.095778",
            "longitude": "101.621916"
        }
    },
    {
        "user_id": "811104-11-9852",
        "transaction_id": "2060f3af-a32a-486a-bde4-c85973b0728b",
        "client_id": 1081,
        "transaction_date": "2023-05-03T22:33:44.700112",
        "transaction_amount": 825,
        "transaction_details": "Electronics",
        "transacted_to": "821308-29-2624",
        "is_anomaly": "Yes",
        "anomaly_type": "Suspicious",
        "user_score": 59,
        "coors": {
            "latitude": "3.076340",
            "longitude": "101.640568"
        }
    },
    {
        "user_id": "811104-11-9852",
        "transaction_id": "1ca10f38-a8df-4d1c-b481-d5770ef45784",
        "client_id": 9415,
        "transaction_date": "2022-11-02T22:33:44.700112",
        "transaction_amount": 312,
        "transaction_details": "Clothing",
        "transacted_to": "745897-40-7940",
        "is_anomaly": "Yes",
        "anomaly_type": "Suspicious",
        "user_score": 38,
        "coors": {
            "latitude": "3.187716",
            "longitude": "101.689718"
        }
    },
    {
        "user_id": "811104-11-9852",
        "transaction_id": "2062995b-5eb2-4941-84b2-98d8237023a6",
        "client_id": 3506,
        "transaction_date": "2022-10-19T22:33:44.700112",
        "transaction_amount": 370,
        "transaction_details": "Electronics",
        "transacted_to": "281513-58-9820",
        "is_anomaly": "No",
        "anomaly_type": "",
        "user_score": 58,
        "coors": {
            "latitude": "3.156942",
            "longitude": "101.702075"
        }
    },
    {
        "user_id": "811104-11-9852",
        "transaction_id": "23e1f258-53cc-4e0f-84ff-220d32d54044",
        "client_id": 5368,
        "transaction_date": "2022-09-11T22:33:44.700112",
        "transaction_amount": 619,
        "transaction_details": "Electronics",
        "transacted_to": "699979-60-1102",
        "is_anomaly": "Yes",
        "anomaly_type": "Fraud",
        "user_score": 19,
        "coors": {
            "latitude": "3.135056",
            "longitude": "101.720302"
        }
    },
    {
        "user_id": "811104-11-9852",
        "transaction_id": "0464b035-a3d9-4d4f-87ff-e8c1bcbc7a51",
        "client_id": 3227,
        "transaction_date": "2022-10-01T22:33:44.700112",
        "transaction_amount": 784,
        "transaction_details": "Clothing",
        "transacted_to": "583604-42-6673",
        "is_anomaly": "No",
        "anomaly_type": "Fraud",
        "user_score": 79,
        "coors": {
            "latitude": "3.105137",
            "longitude": "101.597678"
        }
    },
    {
        "user_id": "811104-11-9852",
        "transaction_id": "36c8622a-560f-4649-8001-11cc76f0b6a3",
        "client_id": 1645,
        "transaction_date": "2022-10-02T22:33:44.700112",
        "transaction_amount": 837,
        "transaction_details": "Clothing",
        "transacted_to": "860823-81-7426",
        "is_anomaly": "Yes",
        "anomaly_type": "Fraud",
        "user_score": 68,
        "coors": {
            "latitude": "3.114286",
            "longitude": "101.591686"
        }
    },
    {
        "user_id": "811104-11-9852",
        "transaction_id": "a4e5dc56-0d69-4c75-929c-822ebb28dd18",
        "client_id": 7758,
        "transaction_date": "2022-10-01T22:33:44.700112",
        "transaction_amount": 74,
        "transaction_details": "Electronics",
        "transacted_to": "997188-49-7998",
        "is_anomaly": "Yes",
        "anomaly_type": "Fraud",
        "user_score": 19,
        "coors": {
            "latitude": "3.045476",
            "longitude": "101.658383"
        }
    },
    {
        "user_id": "811104-11-9852",
        "transaction_id": "be32d300-c602-45e6-87d4-1a1ad99994ef",
        "client_id": 1893,
        "transaction_date": "2023-01-07T22:33:44.700112",
        "transaction_amount": 34,
        "transaction_details": "Clothing",
        "transacted_to": "370207-33-7766",
        "is_anomaly": "No",
        "anomaly_type": "",
        "user_score": 27,
        "coors": {
            "latitude": "3.040576",
            "longitude": "101.619993"
        }
    },
    {
        "user_id": "811104-11-9852",
        "transaction_id": "2d0e632a-f8f0-40fb-bdf6-e8ab85acdc09",
        "client_id": 3116,
        "transaction_date": "2023-03-20T22:33:44.700112",
        "transaction_amount": 285,
        "transaction_details": "Electronics",
        "transacted_to": "672120-78-6763",
        "is_anomaly": "Yes",
        "anomaly_type": "Suspicious",
        "user_score": 0,
        "coors": {
            "latitude": "3.201416",
            "longitude": "101.628508"
        }
    },
    {
        "user_id": "811104-11-9852",
        "transaction_id": "60f4bcde-446f-46ae-81db-f2396e9f6617",
        "client_id": 9984,
        "transaction_date": "2023-05-14T22:33:44.700112",
        "transaction_amount": 294,
        "transaction_details": "Clothing",
        "transacted_to": "577981-68-7676",
        "is_anomaly": "No",
        "anomaly_type": "Fraud",
        "user_score": 58,
        "coors": {
            "latitude": "3.177225",
            "longitude": "101.730768"
        }
    },
    {
        "user_id": "811104-11-9852",
        "transaction_id": "f9edc069-94cd-4568-9c13-8bfe41092fc2",
        "client_id": 6412,
        "transaction_date": "2022-08-30T22:33:44.700112",
        "transaction_amount": 517,
        "transaction_details": "Electronics",
        "transacted_to": "832784-41-4039",
        "is_anomaly": "Yes",
        "anomaly_type": "",
        "user_score": 0,
        "coors": {
            "latitude": "3.158887",
            "longitude": "101.612676"
        }
    },
    {
        "user_id": "811104-11-9852",
        "transaction_id": "41193976-fb56-4603-bf7b-5f2f59458fd0",
        "client_id": 5410,
        "transaction_date": "2023-05-10T22:33:44.700112",
        "transaction_amount": 424,
        "transaction_details": "Electronics",
        "transacted_to": "497528-75-7281",
        "is_anomaly": "Yes",
        "anomaly_type": "Suspicious",
        "user_score": 91,
        "coors": {
            "latitude": "3.168074",
            "longitude": "101.677624"
        }
    },
    {
        "user_id": "811104-11-9852",
        "transaction_id": "9f398eaa-fa98-4c25-b11a-3354bac53590",
        "client_id": 3050,
        "transaction_date": "2022-10-15T22:33:44.700112",
        "transaction_amount": 677,
        "transaction_details": "Books",
        "transacted_to": "609565-57-3209",
        "is_anomaly": "No",
        "anomaly_type": "",
        "user_score": 5,
        "coors": {
            "latitude": "3.130296",
            "longitude": "101.647372"
        }
    },
    {
        "user_id": "811104-11-9852",
        "transaction_id": "edfc9dc5-a981-4e2f-93cd-c286d9b07562",
        "client_id": 5860,
        "transaction_date": "2023-02-24T22:33:44.700112",
        "transaction_amount": 35,
        "transaction_details": "Home Appliances",
        "transacted_to": "989414-42-2442",
        "is_anomaly": "Yes",
        "anomaly_type": "",
        "user_score": 91,
        "coors": {
            "latitude": "3.187652",
            "longitude": "101.706881"
        }
    },
    {
        "user_id": "811104-11-9852",
        "transaction_id": "c40c5be6-3070-4b6e-a435-568936511332",
        "client_id": 2976,
        "transaction_date": "2023-05-04T22:33:44.700112",
        "transaction_amount": 279,
        "transaction_details": "Home Appliances",
        "transacted_to": "746098-34-6459",
        "is_anomaly": "Yes",
        "anomaly_type": "",
        "user_score": 21,
        "coors": {
            "latitude": "3.080477",
            "longitude": "101.593078"
        }
    },
    {
        "user_id": "811104-11-9852",
        "transaction_id": "403e04a0-12ae-49db-9d87-e1fe544f7a6d",
        "client_id": 7595,
        "transaction_date": "2022-06-11T22:33:44.700112",
        "transaction_amount": 407,
        "transaction_details": "Books",
        "transacted_to": "830465-10-1532",
        "is_anomaly": "Yes",
        "anomaly_type": "Fraud",
        "user_score": 61,
        "coors": {
            "latitude": "3.152594",
            "longitude": "101.707896"
        }
    },
    {
        "user_id": "811104-11-9852",
        "transaction_id": "698c3474-a9cd-4339-a28c-d8b3dfc27b16",
        "client_id": 5494,
        "transaction_date": "2022-09-02T22:33:44.700112",
        "transaction_amount": 830,
        "transaction_details": "Clothing",
        "transacted_to": "372628-77-1008",
        "is_anomaly": "Yes",
        "anomaly_type": "",
        "user_score": 31,
        "coors": {
            "latitude": "3.218991",
            "longitude": "101.606131"
        }
    },
    {
        "user_id": "811104-11-9852",
        "transaction_id": "0f0ff1c5-d92b-4474-85a8-fbf808a3efdc",
        "client_id": 6158,
        "transaction_date": "2022-12-19T22:33:44.700112",
        "transaction_amount": 178,
        "transaction_details": "Books",
        "transacted_to": "768487-65-4701",
        "is_anomaly": "No",
        "anomaly_type": "Suspicious",
        "user_score": 100,
        "coors": {
            "latitude": "3.206111",
            "longitude": "101.700385"
        }
    },
    {
        "user_id": "811104-11-9852",
        "transaction_id": "380844cd-590a-4476-ae9a-b8b19c6ddbd1",
        "client_id": 7049,
        "transaction_date": "2022-06-26T22:33:44.700112",
        "transaction_amount": 279,
        "transaction_details": "Electronics",
        "transacted_to": "250087-54-8807",
        "is_anomaly": "Yes",
        "anomaly_type": "",
        "user_score": 23,
        "coors": {
            "latitude": "3.103862",
            "longitude": "101.723737"
        }
    },
    {
        "user_id": "811104-11-9852",
        "transaction_id": "78fb9ee5-4119-473f-a2da-ec30a5f9e7a5",
        "client_id": 8308,
        "transaction_date": "2022-10-27T22:33:44.700112",
        "transaction_amount": 100,
        "transaction_details": "Electronics",
        "transacted_to": "916677-85-4611",
        "is_anomaly": "Yes",
        "anomaly_type": "Fraud",
        "user_score": 64,
        "coors": {
            "latitude": "3.103472",
            "longitude": "101.701155"
        }
    },
    {
        "user_id": "811104-11-9852",
        "transaction_id": "b723d79f-1830-4f89-91b6-daf2b0354092",
        "client_id": 2013,
        "transaction_date": "2022-06-17T22:33:44.700112",
        "transaction_amount": 543,
        "transaction_details": "Home Appliances",
        "transacted_to": "757645-82-4057",
        "is_anomaly": "Yes",
        "anomaly_type": "",
        "user_score": 2,
        "coors": {
            "latitude": "3.220869",
            "longitude": "101.620909"
        }
    },
    {
        "user_id": "811104-11-9852",
        "transaction_id": "c871cf35-86b7-4fe7-a8cc-30824ce7400b",
        "client_id": 7769,
        "transaction_date": "2022-10-22T22:33:44.700112",
        "transaction_amount": 198,
        "transaction_details": "Electronics",
        "transacted_to": "119648-16-8000",
        "is_anomaly": "Yes",
        "anomaly_type": "Suspicious",
        "user_score": 19,
        "coors": {
            "latitude": "3.145374",
            "longitude": "101.732083"
        }
    },
    {
        "user_id": "811104-11-9852",
        "transaction_id": "46e814db-a6f7-4964-8acb-11992649a3d3",
        "client_id": 5371,
        "transaction_date": "2023-05-03T22:33:44.700112",
        "transaction_amount": 565,
        "transaction_details": "Books",
        "transacted_to": "428466-31-7142",
        "is_anomaly": "No",
        "anomaly_type": "Suspicious",
        "user_score": 5,
        "coors": {
            "latitude": "3.102238",
            "longitude": "101.652690"
        }
    },
    {
        "user_id": "811104-11-9852",
        "transaction_id": "6190b5cd-104e-4aba-95cd-b833f6623780",
        "client_id": 3361,
        "transaction_date": "2023-04-22T22:33:44.700112",
        "transaction_amount": 172,
        "transaction_details": "Books",
        "transacted_to": "373854-14-2380",
        "is_anomaly": "Yes",
        "anomaly_type": "Fraud",
        "user_score": 42,
        "coors": {
            "latitude": "3.048151",
            "longitude": "101.658593"
        }
    },
    {
        "user_id": "811104-11-9852",
        "transaction_id": "8eb27836-59fd-4e0b-b4c7-fe6fada9cee0",
        "client_id": 8429,
        "transaction_date": "2022-07-09T22:33:44.701113",
        "transaction_amount": 897,
        "transaction_details": "Electronics",
        "transacted_to": "385077-96-1776",
        "is_anomaly": "Yes",
        "anomaly_type": "",
        "user_score": 96,
        "coors": {
            "latitude": "3.091274",
            "longitude": "101.602443"
        }
    },
    {
        "user_id": "811104-11-9852",
        "transaction_id": "4131d683-622f-4fc6-ab86-a0a63d619238",
        "client_id": 5574,
        "transaction_date": "2023-03-20T22:33:44.701113",
        "transaction_amount": 498,
        "transaction_details": "Clothing",
        "transacted_to": "775906-62-5884",
        "is_anomaly": "No",
        "anomaly_type": "Suspicious",
        "user_score": 60,
        "coors": {
            "latitude": "3.184835",
            "longitude": "101.623197"
        }
    },
    {
        "user_id": "811104-11-9852",
        "transaction_id": "702876fa-287b-418b-8394-00c65065e6f1",
        "client_id": 3614,
        "transaction_date": "2023-02-20T22:33:44.701113",
        "transaction_amount": 812,
        "transaction_details": "Home Appliances",
        "transacted_to": "673256-44-5023",
        "is_anomaly": "Yes",
        "anomaly_type": "Suspicious",
        "user_score": 2,
        "coors": {
            "latitude": "3.229969",
            "longitude": "101.739409"
        }
    },
    {
        "user_id": "811104-11-9852",
        "transaction_id": "7e2a62c5-2246-49b4-b3d7-6ed5fd63532c",
        "client_id": 6499,
        "transaction_date": "2022-09-13T22:33:44.701113",
        "transaction_amount": 843,
        "transaction_details": "Books",
        "transacted_to": "304274-15-2194",
        "is_anomaly": "No",
        "anomaly_type": "",
        "user_score": 80,
        "coors": {
            "latitude": "3.207033",
            "longitude": "101.596812"
        }
    },
    {
        "user_id": "811104-11-9852",
        "transaction_id": "3a8b4473-729b-4603-978b-ca77ebe00df1",
        "client_id": 1341,
        "transaction_date": "2022-07-02T22:33:44.701113",
        "transaction_amount": 294,
        "transaction_details": "Electronics",
        "transacted_to": "570592-84-7602",
        "is_anomaly": "No",
        "anomaly_type": "Suspicious",
        "user_score": 36,
        "coors": {
            "latitude": "3.130793",
            "longitude": "101.612878"
        }
    },
    {
        "user_id": "811104-11-9852",
        "transaction_id": "b8779ff5-d9f8-4284-8223-5f0241a24a5f",
        "client_id": 6845,
        "transaction_date": "2022-07-01T22:33:44.701113",
        "transaction_amount": 624,
        "transaction_details": "Home Appliances",
        "transacted_to": "767448-58-9766",
        "is_anomaly": "No",
        "anomaly_type": "Suspicious",
        "user_score": 84,
        "coors": {
            "latitude": "3.194985",
            "longitude": "101.678375"
        }
    },
    {
        "user_id": "811104-11-9852",
        "transaction_id": "b41bfdae-2600-4115-9873-2b9f338869e4",
        "client_id": 9006,
        "transaction_date": "2022-12-17T22:33:44.701113",
        "transaction_amount": 631,
        "transaction_details": "Books",
        "transacted_to": "327732-80-9776",
        "is_anomaly": "Yes",
        "anomaly_type": "Fraud",
        "user_score": 20,
        "coors": {
            "latitude": "3.129024",
            "longitude": "101.630131"
        }
    },
    {
        "user_id": "811104-11-9852",
        "transaction_id": "90b8c86c-6e43-4eae-8333-341d63525868",
        "client_id": 6511,
        "transaction_date": "2023-04-11T22:33:44.701113",
        "transaction_amount": 208,
        "transaction_details": "Home Appliances",
        "transacted_to": "789316-53-8714",
        "is_anomaly": "No",
        "anomaly_type": "Suspicious",
        "user_score": 29,
        "coors": {
            "latitude": "3.225374",
            "longitude": "101.660927"
        }
    },
    {
        "user_id": "811104-11-9852",
        "transaction_id": "c126864a-7c68-43ec-b3c4-1766cb26f8be",
        "client_id": 3791,
        "transaction_date": "2022-09-16T22:33:44.701113",
        "transaction_amount": 399,
        "transaction_details": "Home Appliances",
        "transacted_to": "619872-15-8872",
        "is_anomaly": "Yes",
        "anomaly_type": "",
        "user_score": 17,
        "coors": {
            "latitude": "3.219121",
            "longitude": "101.594538"
        }
    },
    {
        "user_id": "811104-11-9852",
        "transaction_id": "bbad0e2a-55f2-4343-8a0c-cf6e39055db6",
        "client_id": 5939,
        "transaction_date": "2022-09-19T22:33:44.701113",
        "transaction_amount": 63,
        "transaction_details": "Electronics",
        "transacted_to": "391027-41-3067",
        "is_anomaly": "Yes",
        "anomaly_type": "",
        "user_score": 24,
        "coors": {
            "latitude": "3.156653",
            "longitude": "101.613634"
        }
    },
    {
        "user_id": "811104-11-9852",
        "transaction_id": "acddc61e-b7e9-44d8-9737-688acce7faf0",
        "client_id": 9759,
        "transaction_date": "2022-08-27T22:33:44.701113",
        "transaction_amount": 472,
        "transaction_details": "Books",
        "transacted_to": "817311-17-6301",
        "is_anomaly": "Yes",
        "anomaly_type": "",
        "user_score": 39,
        "coors": {
            "latitude": "3.074874",
            "longitude": "101.665647"
        }
    },
    {
        "user_id": "811104-11-9852",
        "transaction_id": "212f3d7b-f244-46f0-862c-26abf4e97d79",
        "client_id": 4823,
        "transaction_date": "2022-06-04T22:33:44.701113",
        "transaction_amount": 128,
        "transaction_details": "Home Appliances",
        "transacted_to": "556405-60-1590",
        "is_anomaly": "No",
        "anomaly_type": "Suspicious",
        "user_score": 40,
        "coors": {
            "latitude": "3.034399",
            "longitude": "101.659596"
        }
    },
    {
        "user_id": "811104-11-9852",
        "transaction_id": "ff7d394c-99bc-46fd-8217-45fbeaa71719",
        "client_id": 8480,
        "transaction_date": "2023-03-19T22:33:44.701113",
        "transaction_amount": 691,
        "transaction_details": "Home Appliances",
        "transacted_to": "660292-80-6549",
        "is_anomaly": "Yes",
        "anomaly_type": "Suspicious",
        "user_score": 89,
        "coors": {
            "latitude": "3.140940",
            "longitude": "101.719494"
        }
    },
    {
        "user_id": "811104-11-9852",
        "transaction_id": "f98fa586-922f-481f-83a0-c80eadbc8956",
        "client_id": 3592,
        "transaction_date": "2023-03-23T22:33:44.701113",
        "transaction_amount": 833,
        "transaction_details": "Clothing",
        "transacted_to": "524918-79-9296",
        "is_anomaly": "No",
        "anomaly_type": "",
        "user_score": 12,
        "coors": {
            "latitude": "3.215567",
            "longitude": "101.708220"
        }
    },
    {
        "user_id": "811104-11-9852",
        "transaction_id": "a89be3b0-c501-4840-bfcb-de003d48a2af",
        "client_id": 4839,
        "transaction_date": "2022-09-08T22:33:44.701113",
        "transaction_amount": 259,
        "transaction_details": "Clothing",
        "transacted_to": "689208-88-6457",
        "is_anomaly": "No",
        "anomaly_type": "",
        "user_score": 92,
        "coors": {
            "latitude": "3.035058",
            "longitude": "101.718881"
        }
    },
    {
        "user_id": "811104-11-9852",
        "transaction_id": "67774076-a4b2-4f72-a642-2c9a92d20883",
        "client_id": 1735,
        "transaction_date": "2023-03-21T22:33:44.701113",
        "transaction_amount": 181,
        "transaction_details": "Electronics",
        "transacted_to": "740070-90-6145",
        "is_anomaly": "No",
        "anomaly_type": "",
        "user_score": 12,
        "coors": {
            "latitude": "3.177140",
            "longitude": "101.645042"
        }
    },
    {
        "user_id": "811104-11-9852",
        "transaction_id": "d4864993-bb8a-4362-802c-9f5ff1408b12",
        "client_id": 6248,
        "transaction_date": "2023-03-07T22:33:44.701113",
        "transaction_amount": 419,
        "transaction_details": "Home Appliances",
        "transacted_to": "973560-41-2264",
        "is_anomaly": "No",
        "anomaly_type": "Fraud",
        "user_score": 12,
        "coors": {
            "latitude": "3.118001",
            "longitude": "101.602576"
        }
    },
    {
        "user_id": "811104-11-9852",
        "transaction_id": "ff12dbc9-c053-487a-82c0-d8dec8073003",
        "client_id": 2954,
        "transaction_date": "2022-09-15T22:33:44.701113",
        "transaction_amount": 933,
        "transaction_details": "Electronics",
        "transacted_to": "988517-16-4096",
        "is_anomaly": "No",
        "anomaly_type": "",
        "user_score": 76,
        "coors": {
            "latitude": "3.163233",
            "longitude": "101.716517"
        }
    },
    {
        "user_id": "811104-11-9852",
        "transaction_id": "309cce50-046c-4c08-89ba-b99d6d50f61f",
        "client_id": 5294,
        "transaction_date": "2022-10-31T22:33:44.701113",
        "transaction_amount": 801,
        "transaction_details": "Electronics",
        "transacted_to": "316134-23-6797",
        "is_anomaly": "No",
        "anomaly_type": "Fraud",
        "user_score": 59,
        "coors": {
            "latitude": "3.209087",
            "longitude": "101.703056"
        }
    },
    {
        "user_id": "811104-11-9852",
        "transaction_id": "77156824-ab20-4cc3-baa5-c51f8105d8a1",
        "client_id": 1701,
        "transaction_date": "2023-02-07T22:33:44.701113",
        "transaction_amount": 581,
        "transaction_details": "Home Appliances",
        "transacted_to": "671562-88-7149",
        "is_anomaly": "No",
        "anomaly_type": "",
        "user_score": 83,
        "coors": {
            "latitude": "3.105372",
            "longitude": "101.717497"
        }
    },
    {
        "user_id": "811104-11-9852",
        "transaction_id": "99571e8d-24f9-45b2-b816-283038bf6243",
        "client_id": 8415,
        "transaction_date": "2023-04-11T22:33:44.701113",
        "transaction_amount": 720,
        "transaction_details": "Home Appliances",
        "transacted_to": "458843-83-4381",
        "is_anomaly": "No",
        "anomaly_type": "",
        "user_score": 46,
        "coors": {
            "latitude": "3.116631",
            "longitude": "101.628088"
        }
    },
    {
        "user_id": "811104-11-9852",
        "transaction_id": "8b46ce42-6d4f-402c-9a9d-9765080827e8",
        "client_id": 6524,
        "transaction_date": "2022-06-29T22:33:44.701113",
        "transaction_amount": 828,
        "transaction_details": "Home Appliances",
        "transacted_to": "310606-33-5050",
        "is_anomaly": "No",
        "anomaly_type": "",
        "user_score": 45,
        "coors": {
            "latitude": "3.213226",
            "longitude": "101.733278"
        }
    },
    {
        "user_id": "811104-11-9852",
        "transaction_id": "d490dc50-cf52-4054-9a65-ef751267ef3c",
        "client_id": 2986,
        "transaction_date": "2022-08-09T22:33:44.701113",
        "transaction_amount": 340,
        "transaction_details": "Home Appliances",
        "transacted_to": "198351-84-7232",
        "is_anomaly": "Yes",
        "anomaly_type": "",
        "user_score": 69,
        "coors": {
            "latitude": "3.150094",
            "longitude": "101.627995"
        }
    },
    {
        "user_id": "811104-11-9852",
        "transaction_id": "fd2a9148-5f01-491e-8cbf-1eb88611e8a5",
        "client_id": 1898,
        "transaction_date": "2023-04-19T22:33:44.701113",
        "transaction_amount": 859,
        "transaction_details": "Books",
        "transacted_to": "235222-17-4282",
        "is_anomaly": "Yes",
        "anomaly_type": "",
        "user_score": 36,
        "coors": {
            "latitude": "3.114568",
            "longitude": "101.731965"
        }
    },
    {
        "user_id": "811104-11-9852",
        "transaction_id": "84988847-709e-4d69-8467-267853b16fff",
        "client_id": 1979,
        "transaction_date": "2022-07-24T22:33:44.701113",
        "transaction_amount": 685,
        "transaction_details": "Clothing",
        "transacted_to": "953900-35-6455",
        "is_anomaly": "Yes",
        "anomaly_type": "Suspicious",
        "user_score": 62,
        "coors": {
            "latitude": "3.162833",
            "longitude": "101.695161"
        }
    },
    {
        "user_id": "811104-11-9852",
        "transaction_id": "0f16c252-d1e7-4894-814e-43f6d92228cf",
        "client_id": 7868,
        "transaction_date": "2022-07-04T22:33:44.701113",
        "transaction_amount": 964,
        "transaction_details": "Home Appliances",
        "transacted_to": "476970-23-3766",
        "is_anomaly": "Yes",
        "anomaly_type": "",
        "user_score": 69,
        "coors": {
            "latitude": "3.107857",
            "longitude": "101.655867"
        }
    },
    {
        "user_id": "811104-11-9852",
        "transaction_id": "0429e343-1ecd-4c8b-86db-b540c803ce88",
        "client_id": 2279,
        "transaction_date": "2023-01-01T22:33:44.701113",
        "transaction_amount": 260,
        "transaction_details": "Clothing",
        "transacted_to": "509098-72-2806",
        "is_anomaly": "No",
        "anomaly_type": "Suspicious",
        "user_score": 54,
        "coors": {
            "latitude": "3.179229",
            "longitude": "101.678787"
        }
    },
    {
        "user_id": "811104-11-9852",
        "transaction_id": "921ef877-4e3a-4372-8feb-4ed2b285cc1e",
        "client_id": 6681,
        "transaction_date": "2023-02-24T22:33:44.701113",
        "transaction_amount": 583,
        "transaction_details": "Books",
        "transacted_to": "170297-23-3426",
        "is_anomaly": "Yes",
        "anomaly_type": "Suspicious",
        "user_score": 69,
        "coors": {
            "latitude": "3.087325",
            "longitude": "101.637724"
        }
    },
    {
        "user_id": "811104-11-9852",
        "transaction_id": "1715afb5-1e13-4551-a09d-0a70707aac7b",
        "client_id": 8168,
        "transaction_date": "2022-07-15T22:33:44.701113",
        "transaction_amount": 481,
        "transaction_details": "Clothing",
        "transacted_to": "871845-36-5309",
        "is_anomaly": "Yes",
        "anomaly_type": "Suspicious",
        "user_score": 27,
        "coors": {
            "latitude": "3.125787",
            "longitude": "101.720102"
        }
    },
    {
        "user_id": "811104-11-9852",
        "transaction_id": "2b6e331d-77e7-447e-84e7-6905fe9f72ef",
        "client_id": 7534,
        "transaction_date": "2022-06-02T22:33:44.701113",
        "transaction_amount": 50,
        "transaction_details": "Home Appliances",
        "transacted_to": "976474-41-3245",
        "is_anomaly": "Yes",
        "anomaly_type": "",
        "user_score": 27,
        "coors": {
            "latitude": "3.158882",
            "longitude": "101.686321"
        }
    },
    {
        "user_id": "811104-11-9852",
        "transaction_id": "570a8532-663a-4d75-aada-e3cc96f86a05",
        "client_id": 9867,
        "transaction_date": "2023-05-18T22:33:44.701113",
        "transaction_amount": 464,
        "transaction_details": "Clothing",
        "transacted_to": "701073-72-1781",
        "is_anomaly": "No",
        "anomaly_type": "Fraud",
        "user_score": 51,
        "coors": {
            "latitude": "3.075596",
            "longitude": "101.718068"
        }
    },
    {
        "user_id": "811104-11-9852",
        "transaction_id": "4e5a6e0a-18c0-45d9-ad82-de73df0e5814",
        "client_id": 7693,
        "transaction_date": "2022-06-16T22:33:44.701113",
        "transaction_amount": 784,
        "transaction_details": "Books",
        "transacted_to": "139121-10-8096",
        "is_anomaly": "No",
        "anomaly_type": "Suspicious",
        "user_score": 71,
        "coors": {
            "latitude": "3.112207",
            "longitude": "101.675599"
        }
    },
    {
        "user_id": "811104-11-9852",
        "transaction_id": "67c998e5-bd70-485b-bb04-bec0282f1283",
        "client_id": 9589,
        "transaction_date": "2022-12-08T22:33:44.701113",
        "transaction_amount": 562,
        "transaction_details": "Clothing",
        "transacted_to": "717127-11-7657",
        "is_anomaly": "No",
        "anomaly_type": "Suspicious",
        "user_score": 12,
        "coors": {
            "latitude": "3.078636",
            "longitude": "101.591311"
        }
    },
    {
        "user_id": "811104-11-9852",
        "transaction_id": "05bb6b27-1425-4cd0-b91c-1cf259798a32",
        "client_id": 7644,
        "transaction_date": "2022-08-23T22:33:44.701113",
        "transaction_amount": 448,
        "transaction_details": "Clothing",
        "transacted_to": "422316-82-8601",
        "is_anomaly": "Yes",
        "anomaly_type": "Fraud",
        "user_score": 20,
        "coors": {
            "latitude": "3.101457",
            "longitude": "101.639638"
        }
    },
    {
        "user_id": "811104-11-9852",
        "transaction_id": "ea069581-da8d-4068-844e-0ce519586e66",
        "client_id": 5985,
        "transaction_date": "2022-08-10T22:33:44.701113",
        "transaction_amount": 275,
        "transaction_details": "Books",
        "transacted_to": "570674-28-2343",
        "is_anomaly": "No",
        "anomaly_type": "Suspicious",
        "user_score": 59,
        "coors": {
            "latitude": "3.202742",
            "longitude": "101.646665"
        }
    },
    {
        "user_id": "811104-11-9852",
        "transaction_id": "f4463192-15ab-458e-9477-cb41fcc5b01d",
        "client_id": 9464,
        "transaction_date": "2023-04-06T22:33:44.701113",
        "transaction_amount": 404,
        "transaction_details": "Electronics",
        "transacted_to": "607357-13-6520",
        "is_anomaly": "No",
        "anomaly_type": "Suspicious",
        "user_score": 56,
        "coors": {
            "latitude": "3.094552",
            "longitude": "101.617942"
        }
    },
    {
        "user_id": "811104-11-9852",
        "transaction_id": "07b8388a-529f-42fc-9125-1c0ff2ccbb3e",
        "client_id": 7757,
        "transaction_date": "2023-05-11T22:33:44.701113",
        "transaction_amount": 102,
        "transaction_details": "Electronics",
        "transacted_to": "158210-73-9085",
        "is_anomaly": "No",
        "anomaly_type": "Fraud",
        "user_score": 80,
        "coors": {
            "latitude": "3.065785",
            "longitude": "101.666676"
        }
    }
]